setup.py
stpclient/__init__.py
stpclient/client.py
stpclient/magicclient.py
stpclient.egg-info/PKG-INFO
stpclient.egg-info/SOURCES.txt
stpclient.egg-info/dependency_links.txt
stpclient.egg-info/top_level.txt
stpclient/ioloop/__init__.py
stpclient/ioloop/ioloop.py
stpclient/ioloop/iostream.py
stpclient/ioloop/netutil.py
stpclient/ioloop/posix.py
stpclient/ioloop/process.py
stpclient/ioloop/stack_context.py