Metadata-Version: 1.0
Name: stpclient
Version: 0.3.5
Summary: stpclient is an client lib that communicate with simpletp server
Home-page: http://simpletp.org
Author: dccmx
Author-email: dccmx@dccmx.com
License: MIT
Platform: UNKNOWN
